{"type":"entry","author":{"type":"card","name":"Max Glenister","photo":"https://webmention.io/avatar/pbs.twimg.com/65719bcc3ce47f26aab9f71e7365216d6e2ed2b0bf0edf804e774374250c9509.jpg","url":"https://twitter.com/omgmog"},"url":"https://twitter.com/omgmog/status/1512402287846699011","published":"2022-04-08T12:09:39+00:00","wm-received":"2022-04-08T14:39:23Z","wm-id":1376798,"wm-source":"https://brid.gy/post/twitter/omgmog/1512402287846699011","wm-target":"https://blog.omgmog.net/post/adding-support-for-webmentions/","content":{"html":"📢 My blog now supports <a href=\"https://twitter.com/search?q=%23webmentions\">#webmentions</a>! \n\nIt's held together with duct tape, but it should all work... Interactions with this tweet should appear on the post <a href=\"https://blog.omgmog.net/post/adding-support-for-webmentions/\">blog.omgmog.net/post/adding-su…</a>","text":"📢 My blog now supports #webmentions! \n\nIt's held together with duct tape, but it should all work... Interactions with this tweet should appear on the post blog.omgmog.net/post/adding-su…"},"mention-of":"https://blog.omgmog.net/post/adding-support-for-webmentions/","wm-property":"mention-of","wm-private":false}